taxi_zebra/__init__.py
taxi_zebra/backend.py
taxi_zebra/commands.py
taxi_zebra/roles.py
taxi_zebra/ui.py
taxi_zebra/utils.py
taxi_zebra-5.0.0.dist-info/licenses/LICENSE
taxi_zebra-5.0.0.dist-info/METADATA
taxi_zebra-5.0.0.dist-info/WHEEL
taxi_zebra-5.0.0.dist-info/entry_points.txt
taxi_zebra-5.0.0.dist-info/top_level.txt
taxi_zebra-5.0.0.dist-info/RECORD
