Metadata-Version: 2.4
Name: taxi_zebra
Version: 5.0.0
Summary: Zebra backend for Taxi
Author-email: Zebra squad <zebra-squad@liip.ch>
License-Expression: WTFPL
Project-URL: Homepage, https://github.com/liip/taxi-zebra
Requires-Python: >=3.10
License-File: LICENSE
Requires-Dist: requests>=2.3.0
Requires-Dist: taxi~=6.2
Requires-Dist: click>=7.0
Provides-Extra: testing
Requires-Dist: pytest>=7.0; extra == "testing"
Requires-Dist: responses; extra == "testing"
Requires-Dist: ruff; extra == "testing"
Dynamic: license-file
